LICENSE.txt
README.md
setup.cfg
setup.py
IR3/__init__.py
IR3/dnazyme.py
IR3.egg-info/PKG-INFO
IR3.egg-info/SOURCES.txt
IR3.egg-info/dependency_links.txt
IR3.egg-info/requires.txt
IR3.egg-info/top_level.txt