Metadata-Version: 2.1
Name: IR3
Version: 3.0.0
Summary: Finding the activity value and designing enzyme for input substrate
Home-page: https://github.com/XinxinTree/IR3
Download-URL: https://github.com/XinxinTree/IR3/archive/refs/tags/v_05.tar.gz
Author: Xinxin Yu
Author-email: xn255368@dal.ca
License: MIT
Keywords: IR3,dnazyme,substrate
Classifier: Development Status :: 3 - Alpha
Classifier: Intended Audience :: Developers
Classifier: Topic :: Software Development :: Build Tools
Classifier: License :: OSI Approved :: MIT License
Classifier: Programming Language :: Python :: 3
Classifier: Programming Language :: Python :: 3.4
Classifier: Programming Language :: Python :: 3.5
Classifier: Programming Language :: Python :: 3.6
License-File: LICENSE.txt
